blandfeed/__init__.py
blandfeed/main.css
blandfeed/main.html
blandfeed/main.js
blandfeed/main.py
blandfeed/sodium.js
blandfeed-0.1.4.dist-info/entry_points.txt
blandfeed-0.1.4.dist-info/WHEEL
blandfeed-0.1.4.dist-info/METADATA
blandfeed-0.1.4.dist-info/RECORD
